oauth_client/__init__.py
oauth_client/oauth.py
oauth_client/client_management/__init__.py
oauth_client/client_management/client_generator.py
oauth_client/client_management/get_resource.py
oauth_client/client_management/get_token.py
oauth_client/client_management/signature_generator.py
oauth_client/servers/__init__.py
oauth_client/servers/auth_server.py
oauth_client/servers/resource_server.py
steelcut_oauth-0.0.3.dist-info/licenses/LICENSE
steelcut_oauth-0.0.3.dist-info/METADATA
steelcut_oauth-0.0.3.dist-info/WHEEL
steelcut_oauth-0.0.3.dist-info/top_level.txt
steelcut_oauth-0.0.3.dist-info/RECORD
