Metadata-Version: 2.4
Name: steelcut-oauth
Version: 0.0.3
Summary: A package for creating a client credentials oAuth2.0 workflow.
Author-email: John Glauber <johnbglauber@gmail.com>
Project-URL: Homepage, https://github.com/jglauber/OAuth
Project-URL: Issues, https://github.com/jglauber/OAuth/issues
Classifier: Programming Language :: Python :: 3
Classifier: Operating System :: OS Independent
Requires-Python: >=3.8
License-File: LICENSE
Requires-Dist: argon2-cffi==23.1.0
Requires-Dist: argon2-cffi-bindings==21.2.0
Requires-Dist: blinker==1.9.0
Requires-Dist: certifi==2025.4.26
Requires-Dist: cffi==1.17.1
Requires-Dist: charset-normalizer==3.4.2
Requires-Dist: click==8.2.1
Requires-Dist: cryptography==45.0.2
Requires-Dist: Flask==3.1.1
Requires-Dist: idna==3.10
Requires-Dist: itsdangerous==2.2.0
Requires-Dist: jaraco.classes==3.4.0
Requires-Dist: jaraco.context==6.0.1
Requires-Dist: jaraco.functools==4.1.0
Requires-Dist: jeepney==0.9.0
Requires-Dist: Jinja2==3.1.6
Requires-Dist: jwcrypto==1.5.6
Requires-Dist: keyring==25.6.0
Requires-Dist: MarkupSafe==3.0.2
Requires-Dist: more-itertools==10.7.0
Requires-Dist: psycopg2==2.9.10
Requires-Dist: pycparser==2.22
Requires-Dist: PyJWT==2.10.1
Requires-Dist: requests==2.32.3
Requires-Dist: SecretStorage==3.3.3
Requires-Dist: typing_extensions==4.13.2
Requires-Dist: urllib3==2.4.0
Requires-Dist: Werkzeug==3.1.3
Dynamic: license-file
